{
  "Query cross patient #1" : {
    "transaction" : "Query cross patient #1",
    "sampleCount" : 500,
    "errorCount" : 500,
    "errorPct" : 100.0,
    "meanResTime" : 6759.018000000004,
    "medianResTime" : 6559.0,
    "minResTime" : 5348.0,
    "maxResTime" : 19357.0,
    "pct1ResTime" : 7272.7,
    "pct2ResTime" : 7493.85,
    "pct3ResTime" : 16439.92000000008,
    "throughput" : 0.3098934090630187,
    "receivedKBytesPerSec" : 0.17997725517955843,
    "sentKBytesPerSec" : 0.15615722566066176
  },
  "Query participation #2" : {
    "transaction" : "Query participation #2",
    "sampleCount" : 500,
    "errorCount" : 0,
    "errorPct" : 0.0,
    "meanResTime" : 2.4739999999999993,
    "medianResTime" : 2.0,
    "minResTime" : 1.0,
    "maxResTime" : 9.0,
    "pct1ResTime" : 3.0,
    "pct2ResTime" : 4.0,
    "pct3ResTime" : 6.0,
    "throughput" : 0.3109307712637781,
    "receivedKBytesPerSec" : 0.15962833570418045,
    "sentKBytesPerSec" : 0.11234803258554482
  },
  "Query participation #1" : {
    "transaction" : "Query participation #1",
    "sampleCount" : 500,
    "errorCount" : 0,
    "errorPct" : 0.0,
    "meanResTime" : 3.777999999999998,
    "medianResTime" : 4.0,
    "minResTime" : 2.0,
    "maxResTime" : 26.0,
    "pct1ResTime" : 5.0,
    "pct2ResTime" : 5.0,
    "pct3ResTime" : 7.990000000000009,
    "throughput" : 0.3109284510104242,
    "receivedKBytesPerSec" : 0.17845289056966446,
    "sentKBytesPerSec" : 0.13117294027002271
  },
  "Composition - Create 'Laboratory Test Report'" : {
    "transaction" : "Composition - Create 'Laboratory Test Report'",
    "sampleCount" : 500,
    "errorCount" : 0,
    "errorPct" : 0.0,
    "meanResTime" : 13.991999999999985,
    "medianResTime" : 12.0,
    "minResTime" : 8.0,
    "maxResTime" : 386.0,
    "pct1ResTime" : 16.0,
    "pct2ResTime" : 18.0,
    "pct3ResTime" : 72.92000000000007,
    "throughput" : 0.30907143197121434,
    "receivedKBytesPerSec" : 0.16078656496619687,
    "sentKBytesPerSec" : 3.400691234394211
  },
  "Query ehr_id, time_created #2" : {
    "transaction" : "Query ehr_id, time_created #2",
    "sampleCount" : 500,
    "errorCount" : 0,
    "errorPct" : 0.0,
    "meanResTime" : 34.045999999999985,
    "medianResTime" : 34.0,
    "minResTime" : 24.0,
    "maxResTime" : 54.0,
    "pct1ResTime" : 40.0,
    "pct2ResTime" : 42.0,
    "pct3ResTime" : 46.99000000000001,
    "throughput" : 0.3108654307071629,
    "receivedKBytesPerSec" : 1.29285714688174,
    "sentKBytesPerSec" : 0.12932487644653456
  },
  "Query ehr_id, time_created #3" : {
    "transaction" : "Query ehr_id, time_created #3",
    "sampleCount" : 500,
    "errorCount" : 0,
    "errorPct" : 0.0,
    "meanResTime" : 2.42,
    "medianResTime" : 2.0,
    "minResTime" : 1.0,
    "maxResTime" : 9.0,
    "pct1ResTime" : 3.0,
    "pct2ResTime" : 4.0,
    "pct3ResTime" : 7.990000000000009,
    "throughput" : 0.3108723887496526,
    "receivedKBytesPerSec" : 0.19420720293656277,
    "sentKBytesPerSec" : 0.13145287532089803
  },
  "Query ehr_id, time_created #1" : {
    "transaction" : "Query ehr_id, time_created #1",
    "sampleCount" : 500,
    "errorCount" : 0,
    "errorPct" : 0.0,
    "meanResTime" : 29.972000000000012,
    "medianResTime" : 30.0,
    "minResTime" : 21.0,
    "maxResTime" : 44.0,
    "pct1ResTime" : 35.0,
    "pct2ResTime" : 36.0,
    "pct3ResTime" : 38.99000000000001,
    "throughput" : 0.3108685231320377,
    "receivedKBytesPerSec" : 1.2758693855978966,
    "sentKBytesPerSec" : 0.11293270566906057
  },
  "Query ehr_id, time_created #4" : {
    "transaction" : "Query ehr_id, time_created #4",
    "sampleCount" : 500,
    "errorCount" : 0,
    "errorPct" : 0.0,
    "meanResTime" : 867.2579999999994,
    "medianResTime" : 876.0,
    "minResTime" : 668.0,
    "maxResTime" : 1102.0,
    "pct1ResTime" : 1012.0,
    "pct2ResTime" : 1060.85,
    "pct3ResTime" : 1078.99,
    "throughput" : 0.3107282662667801,
    "receivedKBytesPerSec" : 1.3141347753947337,
    "sentKBytesPerSec" : 0.15111589511802392
  },
  "Query ehr_id, start_time, magnitude #1" : {
    "transaction" : "Query ehr_id, start_time, magnitude #1",
    "sampleCount" : 500,
    "errorCount" : 0,
    "errorPct" : 0.0,
    "meanResTime" : 5.9719999999999995,
    "medianResTime" : 6.0,
    "minResTime" : 3.0,
    "maxResTime" : 21.0,
    "pct1ResTime" : 8.0,
    "pct2ResTime" : 9.0,
    "pct3ResTime" : 12.0,
    "throughput" : 0.31081943815035085,
    "receivedKBytesPerSec" : 0.46219518229093814,
    "sentKBytesPerSec" : 0.1587485997584311
  },
  "Query start_time #5" : {
    "transaction" : "Query start_time #5",
    "sampleCount" : 500,
    "errorCount" : 0,
    "errorPct" : 0.0,
    "meanResTime" : 3.936,
    "medianResTime" : 4.0,
    "minResTime" : 2.0,
    "maxResTime" : 14.0,
    "pct1ResTime" : 5.0,
    "pct2ResTime" : 5.0,
    "pct3ResTime" : 9.990000000000009,
    "throughput" : 0.30925054984747763,
    "receivedKBytesPerSec" : 0.2982908794822775,
    "sentKBytesPerSec" : 0.16912139444783933
  },
  "Query ehr_id, start_time, magnitude #5" : {
    "transaction" : "Query ehr_id, start_time, magnitude #5",
    "sampleCount" : 500,
    "errorCount" : 0,
    "errorPct" : 0.0,
    "meanResTime" : 8.234000000000007,
    "medianResTime" : 8.0,
    "minResTime" : 5.0,
    "maxResTime" : 23.0,
    "pct1ResTime" : 10.0,
    "pct2ResTime" : 11.0,
    "pct3ResTime" : 15.990000000000009,
    "throughput" : 0.3108712290542738,
    "receivedKBytesPerSec" : 0.5065956334327707,
    "sentKBytesPerSec" : 0.20309848851299722
  },
  "Setup - Upload template 'Corona Anamnese'" : {
    "transaction" : "Setup - Upload template 'Corona Anamnese'",
    "sampleCount" : 1,
    "errorCount" : 0,
    "errorPct" : 0.0,
    "meanResTime" : 515.0,
    "medianResTime" : 515.0,
    "minResTime" : 515.0,
    "maxResTime" : 515.0,
    "pct1ResTime" : 515.0,
    "pct2ResTime" : 515.0,
    "pct3ResTime" : 515.0,
    "throughput" : 1.941747572815534,
    "receivedKBytesPerSec" : 0.8400333737864077,
    "sentKBytesPerSec" : 2296.6796875
  },
  "Query start_time #6" : {
    "transaction" : "Query start_time #6",
    "sampleCount" : 500,
    "errorCount" : 0,
    "errorPct" : 0.0,
    "meanResTime" : 4.227999999999998,
    "medianResTime" : 4.0,
    "minResTime" : 3.0,
    "maxResTime" : 12.0,
    "pct1ResTime" : 5.0,
    "pct2ResTime" : 6.0,
    "pct3ResTime" : 10.0,
    "throughput" : 0.3092524625773595,
    "receivedKBytesPerSec" : 0.3106749031034722,
    "sentKBytesPerSec" : 0.1815046191494073
  },
  "Query ehr_id, start_time, magnitude #4" : {
    "transaction" : "Query ehr_id, start_time, magnitude #4",
    "sampleCount" : 500,
    "errorCount" : 0,
    "errorPct" : 0.0,
    "meanResTime" : 8.348,
    "medianResTime" : 8.0,
    "minResTime" : 5.0,
    "maxResTime" : 18.0,
    "pct1ResTime" : 10.0,
    "pct2ResTime" : 11.949999999999989,
    "pct3ResTime" : 15.0,
    "throughput" : 0.310870649209829,
    "receivedKBytesPerSec" : 0.48837961141635156,
    "sentKBytesPerSec" : 0.18488303258670494
  },
  "Query ehr_id, start_time, magnitude #3" : {
    "transaction" : "Query ehr_id, start_time, magnitude #3",
    "sampleCount" : 500,
    "errorCount" : 0,
    "errorPct" : 0.0,
    "meanResTime" : 6.695999999999998,
    "medianResTime" : 6.0,
    "minResTime" : 5.0,
    "maxResTime" : 19.0,
    "pct1ResTime" : 8.0,
    "pct2ResTime" : 9.0,
    "pct3ResTime" : 12.980000000000018,
    "throughput" : 0.3108702626480675,
    "receivedKBytesPerSec" : 0.4810929823447452,
    "sentKBytesPerSec" : 0.17759678090734327
  },
  "Query ehr_id, start_time, magnitude #2" : {
    "transaction" : "Query ehr_id, start_time, magnitude #2",
    "sampleCount" : 500,
    "errorCount" : 0,
    "errorPct" : 0.0,
    "meanResTime" : 1628.953999999999,
    "medianResTime" : 1607.5,
    "minResTime" : 1330.0,
    "maxResTime" : 2012.0,
    "pct1ResTime" : 1823.9,
    "pct2ResTime" : 1885.95,
    "pct3ResTime" : 1990.0,
    "throughput" : 0.3105651789352335,
    "receivedKBytesPerSec" : 0.47425183198516985,
    "sentKBytesPerSec" : 0.17105347746042157
  },
  "Composition - Create 'Blood Pressure'" : {
    "transaction" : "Composition - Create 'Blood Pressure'",
    "sampleCount" : 500,
    "errorCount" : 0,
    "errorPct" : 0.0,
    "meanResTime" : 12.13399999999999,
    "medianResTime" : 11.0,
    "minResTime" : 8.0,
    "maxResTime" : 76.0,
    "pct1ResTime" : 14.0,
    "pct2ResTime" : 17.94999999999999,
    "pct3ResTime" : 40.99000000000001,
    "throughput" : 0.30906436327178005,
    "receivedKBytesPerSec" : 0.16078288765479487,
    "sentKBytesPerSec" : 2.4918314288787267
  },
  "Query ehr_id, start_time, magnitude #7" : {
    "transaction" : "Query ehr_id, start_time, magnitude #7",
    "sampleCount" : 500,
    "errorCount" : 0,
    "errorPct" : 0.0,
    "meanResTime" : 11.589999999999996,
    "medianResTime" : 11.0,
    "minResTime" : 8.0,
    "maxResTime" : 22.0,
    "pct1ResTime" : 14.0,
    "pct2ResTime" : 15.0,
    "pct3ResTime" : 21.0,
    "throughput" : 0.3108720021835649,
    "receivedKBytesPerSec" : 0.5627602921559534,
    "sentKBytesPerSec" : 0.2592623924460591
  },
  "Query ehr_id, start_time, magnitude #6" : {
    "transaction" : "Query ehr_id, start_time, magnitude #6",
    "sampleCount" : 500,
    "errorCount" : 0,
    "errorPct" : 0.0,
    "meanResTime" : 8.225999999999992,
    "medianResTime" : 8.0,
    "minResTime" : 5.0,
    "maxResTime" : 25.0,
    "pct1ResTime" : 10.0,
    "pct2ResTime" : 11.0,
    "pct3ResTime" : 15.0,
    "throughput" : 0.3108718089008816,
    "receivedKBytesPerSec" : 0.5263296521577612,
    "sentKBytesPerSec" : 0.2228319411457491
  },
  "Setup - Upload template 'Blood Pressure'" : {
    "transaction" : "Setup - Upload template 'Blood Pressure'",
    "sampleCount" : 1,
    "errorCount" : 0,
    "errorPct" : 0.0,
    "meanResTime" : 63.0,
    "medianResTime" : 63.0,
    "minResTime" : 63.0,
    "maxResTime" : 63.0,
    "pct1ResTime" : 63.0,
    "pct2ResTime" : 63.0,
    "pct3ResTime" : 63.0,
    "throughput" : 15.873015873015872,
    "receivedKBytesPerSec" : 7.486979166666667,
    "sentKBytesPerSec" : 2164.8065476190477
  },
  "Setup - Upload template 'International Patient Summary'" : {
    "transaction" : "Setup - Upload template 'International Patient Summary'",
    "sampleCount" : 1,
    "errorCount" : 0,
    "errorPct" : 0.0,
    "meanResTime" : 585.0,
    "medianResTime" : 585.0,
    "minResTime" : 585.0,
    "maxResTime" : 585.0,
    "pct1ResTime" : 585.0,
    "pct2ResTime" : 585.0,
    "pct3ResTime" : 585.0,
    "throughput" : 1.7094017094017093,
    "receivedKBytesPerSec" : 0.7929353632478633,
    "sentKBytesPerSec" : 3269.1339476495727
  },
  "Query start_time #1" : {
    "transaction" : "Query start_time #1",
    "sampleCount" : 500,
    "errorCount" : 0,
    "errorPct" : 0.0,
    "meanResTime" : 2.417999999999999,
    "medianResTime" : 2.0,
    "minResTime" : 1.0,
    "maxResTime" : 17.0,
    "pct1ResTime" : 3.0,
    "pct2ResTime" : 4.0,
    "pct3ResTime" : 7.0,
    "throughput" : 0.3092501673043405,
    "receivedKBytesPerSec" : 0.2599362416997255,
    "sentKBytesPerSec" : 0.1307669164480268
  },
  "Query start_time #2" : {
    "transaction" : "Query start_time #2",
    "sampleCount" : 500,
    "errorCount" : 0,
    "errorPct" : 0.0,
    "meanResTime" : 579.274,
    "medianResTime" : 579.5,
    "minResTime" : 439.0,
    "maxResTime" : 743.0,
    "pct1ResTime" : 667.0,
    "pct2ResTime" : 676.0,
    "pct3ResTime" : 709.9300000000001,
    "throughput" : 0.3091518850845345,
    "receivedKBytesPerSec" : 0.2722317834956793,
    "sentKBytesPerSec" : 0.14310350930670834
  },
  "Query start_time #3" : {
    "transaction" : "Query start_time #3",
    "sampleCount" : 500,
    "errorCount" : 0,
    "errorPct" : 0.0,
    "meanResTime" : 3.4019999999999997,
    "medianResTime" : 3.0,
    "minResTime" : 2.0,
    "maxResTime" : 15.0,
    "pct1ResTime" : 4.0,
    "pct2ResTime" : 5.0,
    "pct3ResTime" : 9.0,
    "throughput" : 0.30925227130330657,
    "receivedKBytesPerSec" : 0.2801722896589751,
    "sentKBytesPerSec" : 0.15100208559731765
  },
  "Query start_time #4" : {
    "transaction" : "Query start_time #4",
    "sampleCount" : 500,
    "errorCount" : 0,
    "errorPct" : 0.0,
    "meanResTime" : 780.6219999999993,
    "medianResTime" : 759.5,
    "minResTime" : 619.0,
    "maxResTime" : 1032.0,
    "pct1ResTime" : 903.9000000000001,
    "pct2ResTime" : 916.95,
    "pct3ResTime" : 941.9300000000001,
    "throughput" : 0.30912493531560725,
    "receivedKBytesPerSec" : 0.2924340000874823,
    "sentKBytesPerSec" : 0.1633169824274839
  },
  "Setup - Upload template 'Laboratory Test Report'" : {
    "transaction" : "Setup - Upload template 'Laboratory Test Report'",
    "sampleCount" : 1,
    "errorCount" : 0,
    "errorPct" : 0.0,
    "meanResTime" : 47.0,
    "medianResTime" : 47.0,
    "minResTime" : 47.0,
    "maxResTime" : 47.0,
    "pct1ResTime" : 47.0,
    "pct2ResTime" : 47.0,
    "pct3ResTime" : 47.0,
    "throughput" : 21.27659574468085,
    "receivedKBytesPerSec" : 10.077293882978724,
    "sentKBytesPerSec" : 1400.9931848404256
  },
  "Composition - Create 'Corona Anamnese'" : {
    "transaction" : "Composition - Create 'Corona Anamnese'",
    "sampleCount" : 500,
    "errorCount" : 0,
    "errorPct" : 0.0,
    "meanResTime" : 23.848,
    "medianResTime" : 21.0,
    "minResTime" : 16.0,
    "maxResTime" : 645.0,
    "pct1ResTime" : 26.0,
    "pct2ResTime" : 32.0,
    "pct3ResTime" : 86.94000000000005,
    "throughput" : 0.30894309947782433,
    "receivedKBytesPerSec" : 0.16071980324495294,
    "sentKBytesPerSec" : 14.092511891219898
  },
  "Composition - Get composition by version ID" : {
    "transaction" : "Composition - Get composition by version ID",
    "sampleCount" : 500,
    "errorCount" : 0,
    "errorPct" : 0.0,
    "meanResTime" : 31.388000000000055,
    "medianResTime" : 28.0,
    "minResTime" : 20.0,
    "maxResTime" : 241.0,
    "pct1ResTime" : 38.900000000000034,
    "pct2ResTime" : 52.0,
    "pct3ResTime" : 121.93000000000006,
    "throughput" : 0.3091792219195701,
    "receivedKBytesPerSec" : 69.92725483923454,
    "sentKBytesPerSec" : 0.09541077551424235
  },
  "Get existing EHR Id" : {
    "transaction" : "Get existing EHR Id",
    "sampleCount" : 1,
    "errorCount" : 0,
    "errorPct" : 0.0,
    "meanResTime" : 530.0,
    "medianResTime" : 530.0,
    "minResTime" : 530.0,
    "maxResTime" : 530.0,
    "pct1ResTime" : 530.0,
    "pct2ResTime" : 530.0,
    "pct3ResTime" : 530.0,
    "throughput" : 1.8867924528301887,
    "receivedKBytesPerSec" : 0.9894604952830188,
    "sentKBytesPerSec" : 0.773879716981132
  },
  "Query composer #2" : {
    "transaction" : "Query composer #2",
    "sampleCount" : 500,
    "errorCount" : 0,
    "errorPct" : 0.0,
    "meanResTime" : 2.740000000000001,
    "medianResTime" : 3.0,
    "minResTime" : 1.0,
    "maxResTime" : 7.0,
    "pct1ResTime" : 4.0,
    "pct2ResTime" : 4.0,
    "pct3ResTime" : 6.0,
    "throughput" : 0.310880120273301,
    "receivedKBytesPerSec" : 0.33781193225518036,
    "sentKBytesPerSec" : 0.1332777078124796
  },
  "Query composer #1" : {
    "transaction" : "Query composer #1",
    "sampleCount" : 500,
    "errorCount" : 0,
    "errorPct" : 0.0,
    "meanResTime" : 3.4719999999999995,
    "medianResTime" : 3.0,
    "minResTime" : 2.0,
    "maxResTime" : 9.0,
    "pct1ResTime" : 4.0,
    "pct2ResTime" : 5.0,
    "pct3ResTime" : 7.0,
    "throughput" : 0.31087934710363035,
    "receivedKBytesPerSec" : 0.3189883191359917,
    "sentKBytesPerSec" : 0.11445460337702018
  },
  "Query ehr_status #1" : {
    "transaction" : "Query ehr_status #1",
    "sampleCount" : 500,
    "errorCount" : 0,
    "errorPct" : 0.0,
    "meanResTime" : 1.9039999999999995,
    "medianResTime" : 2.0,
    "minResTime" : 1.0,
    "maxResTime" : 11.0,
    "pct1ResTime" : 3.0,
    "pct2ResTime" : 3.0,
    "pct3ResTime" : 5.990000000000009,
    "throughput" : 0.31093231811858585,
    "receivedKBytesPerSec" : 0.17632959614711327,
    "sentKBytesPerSec" : 0.12054700223933455
  },
  "Query ehr_status #2" : {
    "transaction" : "Query ehr_status #2",
    "sampleCount" : 500,
    "errorCount" : 0,
    "errorPct" : 0.0,
    "meanResTime" : 90.3459999999999,
    "medianResTime" : 89.0,
    "minResTime" : 66.0,
    "maxResTime" : 117.0,
    "pct1ResTime" : 109.0,
    "pct2ResTime" : 112.0,
    "pct3ResTime" : 115.0,
    "throughput" : 0.31091762361929254,
    "receivedKBytesPerSec" : 0.2831991960214359,
    "sentKBytesPerSec" : 0.10141258426644895
  },
  "Composition - Create International Patient Summary'" : {
    "transaction" : "Composition - Create International Patient Summary'",
    "sampleCount" : 500,
    "errorCount" : 0,
    "errorPct" : 0.0,
    "meanResTime" : 84.96999999999991,
    "medianResTime" : 80.0,
    "minResTime" : 57.0,
    "maxResTime" : 437.0,
    "pct1ResTime" : 96.90000000000003,
    "pct2ResTime" : 113.0,
    "pct3ResTime" : 384.0400000000009,
    "throughput" : 0.3091308600391483,
    "receivedKBytesPerSec" : 0.16081748090962372,
    "sentKBytesPerSec" : 91.40794249145871
  },
  "Query ehr_status #3" : {
    "transaction" : "Query ehr_status #3",
    "sampleCount" : 500,
    "errorCount" : 0,
    "errorPct" : 0.0,
    "meanResTime" : 205.45799999999977,
    "medianResTime" : 261.0,
    "minResTime" : 12.0,
    "maxResTime" : 356.0,
    "pct1ResTime" : 332.0,
    "pct2ResTime" : 338.0,
    "pct3ResTime" : 347.99,
    "throughput" : 0.31087625446340583,
    "receivedKBytesPerSec" : 0.17326190154766635,
    "sentKBytesPerSec" : 0.13024014957500107
  },
  "Query composer #4" : {
    "transaction" : "Query composer #4",
    "sampleCount" : 500,
    "errorCount" : 0,
    "errorPct" : 0.0,
    "meanResTime" : 441.0780000000004,
    "medianResTime" : 435.0,
    "minResTime" : 319.0,
    "maxResTime" : 550.0,
    "pct1ResTime" : 513.0,
    "pct2ResTime" : 520.95,
    "pct3ResTime" : 536.0,
    "throughput" : 0.3108209838976081,
    "receivedKBytesPerSec" : 0.1671603750412615,
    "sentKBytesPerSec" : 0.13234174705015345
  },
  "Create EHR" : {
    "transaction" : "Create EHR",
    "sampleCount" : 500,
    "errorCount" : 0,
    "errorPct" : 0.0,
    "meanResTime" : 7.232000000000002,
    "medianResTime" : 6.0,
    "minResTime" : 4.0,
    "maxResTime" : 255.0,
    "pct1ResTime" : 8.0,
    "pct2ResTime" : 10.0,
    "pct3ResTime" : 23.980000000000018,
    "throughput" : 0.30889748310330767,
    "receivedKBytesPerSec" : 0.13927837590198064,
    "sentKBytesPerSec" : 0.2241316698689039
  },
  "Query composer #3" : {
    "transaction" : "Query composer #3",
    "sampleCount" : 500,
    "errorCount" : 0,
    "errorPct" : 0.0,
    "meanResTime" : 413.53400000000005,
    "medianResTime" : 416.5,
    "minResTime" : 310.0,
    "maxResTime" : 524.0,
    "pct1ResTime" : 475.0,
    "pct2ResTime" : 483.0,
    "pct3ResTime" : 500.98,
    "throughput" : 0.31081480100082365,
    "receivedKBytesPerSec" : 0.15987232796400766,
    "sentKBytesPerSec" : 0.12505439259017515
  },
  "Query ehr_id #4" : {
    "transaction" : "Query ehr_id #4",
    "sampleCount" : 500,
    "errorCount" : 0,
    "errorPct" : 0.0,
    "meanResTime" : 3.697999999999998,
    "medianResTime" : 3.0,
    "minResTime" : 2.0,
    "maxResTime" : 17.0,
    "pct1ResTime" : 5.0,
    "pct2ResTime" : 6.0,
    "pct3ResTime" : 10.0,
    "throughput" : 0.3092486371412561,
    "receivedKBytesPerSec" : 0.18987081118855387,
    "sentKBytesPerSec" : 0.15462431857062808
  },
  "Query ehr_id #3" : {
    "transaction" : "Query ehr_id #3",
    "sampleCount" : 500,
    "errorCount" : 0,
    "errorPct" : 0.0,
    "meanResTime" : 4.304000000000006,
    "medianResTime" : 4.0,
    "minResTime" : 2.0,
    "maxResTime" : 40.0,
    "pct1ResTime" : 5.0,
    "pct2ResTime" : 6.0,
    "pct3ResTime" : 9.990000000000009,
    "throughput" : 0.30924194285579987,
    "receivedKBytesPerSec" : 0.1811088726074724,
    "sentKBytesPerSec" : 0.14586314296811653
  },
  "Query ehr_id #2" : {
    "transaction" : "Query ehr_id #2",
    "sampleCount" : 500,
    "errorCount" : 0,
    "errorPct" : 0.0,
    "meanResTime" : 679.6440000000003,
    "medianResTime" : 689.0,
    "minResTime" : 538.0,
    "maxResTime" : 869.0,
    "pct1ResTime" : 791.0,
    "pct2ResTime" : 826.9,
    "pct3ResTime" : 857.95,
    "throughput" : 0.30910525157458213,
    "receivedKBytesPerSec" : 0.2824539794441917,
    "sentKBytesPerSec" : 0.1361391293556021
  },
  "Query ehr_id #1" : {
    "transaction" : "Query ehr_id #1",
    "sampleCount" : 500,
    "errorCount" : 0,
    "errorPct" : 0.0,
    "meanResTime" : 246.94000000000008,
    "medianResTime" : 240.0,
    "minResTime" : 169.0,
    "maxResTime" : 338.0,
    "pct1ResTime" : 292.90000000000003,
    "pct2ResTime" : 298.0,
    "pct3ResTime" : 309.99,
    "throughput" : 0.3091859134897814,
    "receivedKBytesPerSec" : 0.27377144494171846,
    "sentKBytesPerSec" : 0.12711647419843553
  },
  "Query magnitude #1" : {
    "transaction" : "Query magnitude #1",
    "sampleCount" : 500,
    "errorCount" : 0,
    "errorPct" : 0.0,
    "meanResTime" : 4.601999999999999,
    "medianResTime" : 4.0,
    "minResTime" : 3.0,
    "maxResTime" : 40.0,
    "pct1ResTime" : 5.0,
    "pct2ResTime" : 6.0,
    "pct3ResTime" : 9.990000000000009,
    "throughput" : 0.3092541840544831,
    "receivedKBytesPerSec" : 0.2061825429646838,
    "sentKBytesPerSec" : 0.1446608927364233
  },
  "Query magnitude #2" : {
    "transaction" : "Query magnitude #2",
    "sampleCount" : 500,
    "errorCount" : 0,
    "errorPct" : 0.0,
    "meanResTime" : 1036.486,
    "medianResTime" : 985.5,
    "minResTime" : 851.0,
    "maxResTime" : 8759.0,
    "pct1ResTime" : 1170.9,
    "pct2ResTime" : 1204.85,
    "pct3ResTime" : 1233.91,
    "throughput" : 0.3090993278326017,
    "receivedKBytesPerSec" : 0.2323406676035467,
    "sentKBytesPerSec" : 0.1708498237824732
  },
  "Query single patient #2" : {
    "transaction" : "Query single patient #2",
    "sampleCount" : 500,
    "errorCount" : 0,
    "errorPct" : 0.0,
    "meanResTime" : 134.14000000000007,
    "medianResTime" : 136.0,
    "minResTime" : 118.0,
    "maxResTime" : 167.0,
    "pct1ResTime" : 148.0,
    "pct2ResTime" : 150.95,
    "pct3ResTime" : 154.0,
    "throughput" : 0.3108942312953595,
    "receivedKBytesPerSec" : 6.011039771572018,
    "sentKBytesPerSec" : 0.15666154623867723
  },
  "Query single patient #1" : {
    "transaction" : "Query single patient #1",
    "sampleCount" : 500,
    "errorCount" : 0,
    "errorPct" : 0.0,
    "meanResTime" : 182.81200000000027,
    "medianResTime" : 175.5,
    "minResTime" : 161.0,
    "maxResTime" : 252.0,
    "pct1ResTime" : 202.0,
    "pct2ResTime" : 204.0,
    "pct3ResTime" : 211.0,
    "throughput" : 0.310867750020051,
    "receivedKBytesPerSec" : 0.6025218087327103,
    "sentKBytesPerSec" : 0.22222186817839581
  },
  "Total" : {
    "transaction" : "Total",
    "sampleCount" : 23505,
    "errorCount" : 500,
    "errorPct" : 2.127207,
    "meanResTime" : 343.47985534992876,
    "medianResTime" : 10.0,
    "minResTime" : 1.0,
    "maxResTime" : 19357.0,
    "pct1ResTime" : 861.8000000000029,
    "pct2ResTime" : 1582.0,
    "pct3ResTime" : 6605.94000000001,
    "throughput" : 14.376612819865109,
    "receivedKBytesPerSec" : 90.5620000602466,
    "sentKBytesPerSec" : 118.96769794945953
  },
  "Query magnitude #7" : {
    "transaction" : "Query magnitude #7",
    "sampleCount" : 500,
    "errorCount" : 0,
    "errorPct" : 0.0,
    "meanResTime" : 7.511999999999998,
    "medianResTime" : 7.0,
    "minResTime" : 5.0,
    "maxResTime" : 17.0,
    "pct1ResTime" : 9.0,
    "pct2ResTime" : 10.0,
    "pct3ResTime" : 13.990000000000009,
    "throughput" : 0.3108151874246662,
    "receivedKBytesPerSec" : 0.2536634377760427,
    "sentKBytesPerSec" : 0.19183124848866115
  },
  "Query magnitude #8" : {
    "transaction" : "Query magnitude #8",
    "sampleCount" : 500,
    "errorCount" : 0,
    "errorPct" : 0.0,
    "meanResTime" : 7.320000000000004,
    "medianResTime" : 7.0,
    "minResTime" : 5.0,
    "maxResTime" : 21.0,
    "pct1ResTime" : 9.0,
    "pct2ResTime" : 10.0,
    "pct3ResTime" : 15.0,
    "throughput" : 0.3108173127729753,
    "receivedKBytesPerSec" : 0.2585216928338582,
    "sentKBytesPerSec" : 0.19668908073914843
  },
  "Query magnitude #5" : {
    "transaction" : "Query magnitude #5",
    "sampleCount" : 500,
    "errorCount" : 0,
    "errorPct" : 0.0,
    "meanResTime" : 8.518,
    "medianResTime" : 8.0,
    "minResTime" : 6.0,
    "maxResTime" : 17.0,
    "pct1ResTime" : 10.0,
    "pct2ResTime" : 11.0,
    "pct3ResTime" : 15.0,
    "throughput" : 0.3108115164369562,
    "receivedKBytesPerSec" : 0.25153575369772463,
    "sentKBytesPerSec" : 0.18970429470029068
  },
  "Query magnitude #6" : {
    "transaction" : "Query magnitude #6",
    "sampleCount" : 500,
    "errorCount" : 0,
    "errorPct" : 0.0,
    "meanResTime" : 10.239999999999993,
    "medianResTime" : 10.0,
    "minResTime" : 7.0,
    "maxResTime" : 20.0,
    "pct1ResTime" : 12.0,
    "pct2ResTime" : 13.949999999999989,
    "pct3ResTime" : 17.99000000000001,
    "throughput" : 0.3108130621054228,
    "receivedKBytesPerSec" : 0.27794397373101243,
    "sentKBytesPerSec" : 0.2161122072451768
  },
  "Query magnitude #3" : {
    "transaction" : "Query magnitude #3",
    "sampleCount" : 500,
    "errorCount" : 0,
    "errorPct" : 0.0,
    "meanResTime" : 7.946000000000003,
    "medianResTime" : 8.0,
    "minResTime" : 5.0,
    "maxResTime" : 29.0,
    "pct1ResTime" : 9.0,
    "pct2ResTime" : 10.0,
    "pct3ResTime" : 15.0,
    "throughput" : 0.31078079946495973,
    "receivedKBytesPerSec" : 0.23330108237959885,
    "sentKBytesPerSec" : 0.17147573407978736
  },
  "Query magnitude #4" : {
    "transaction" : "Query magnitude #4",
    "sampleCount" : 500,
    "errorCount" : 0,
    "errorPct" : 0.0,
    "meanResTime" : 1726.383999999999,
    "medianResTime" : 1692.0,
    "minResTime" : 1495.0,
    "maxResTime" : 2150.0,
    "pct1ResTime" : 1983.8000000000002,
    "pct2ResTime" : 2046.95,
    "pct3ResTime" : 2130.9300000000003,
    "throughput" : 0.3104959427495161,
    "receivedKBytesPerSec" : 0.2594672687208871,
    "sentKBytesPerSec" : 0.19769858854754344
  }
}